deeprehab_diagnostics/__init__.py
deeprehab_diagnostics/deeprehab_diagnostics.py
deeprehab_diagnostics/test_diagnostics.py
deeprehab_diagnostics-0.1.0.dist-info/METADATA
deeprehab_diagnostics-0.1.0.dist-info/WHEEL
deeprehab_diagnostics-0.1.0.dist-info/top_level.txt
deeprehab_diagnostics-0.1.0.dist-info/RECORD
