Metadata-Version: 2.4
Name: deeprehab-diagnostics
Version: 0.1.0
Summary: Diagnostics functions for DeepRehab movement analysis results
Author: DeepRehab Team
License: MIT
Project-URL: Homepage, https://github.com/wenjiangbaobeiovo2005/Deeprehab-packge
Project-URL: Repository, https://github.com/wenjiangbaobeiovo2005/Deeprehab-packge
Project-URL: Documentation, https://github.com/wenjiangbaobeiovo2005/Deeprehab-packge#readme
Project-URL: Bug Tracker, https://github.com/wenjiangbaobeiovo2005/Deeprehab-packge/issues
Classifier: Development Status :: 3 - Alpha
Classifier: Intended Audience :: Developers
Classifier: Intended Audience :: Healthcare Industry
Classifier: License :: OSI Approved :: MIT License
Classifier: Operating System :: OS Independent
Classifier: Programming Language :: Python :: 3
Classifier: Programming Language :: Python :: 3.8
Classifier: Programming Language :: Python :: 3.9
Classifier: Programming Language :: Python :: 3.10
Classifier: Programming Language :: Python :: 3.11
Classifier: Topic :: Scientific/Engineering :: Artificial Intelligence
Classifier: Topic :: Scientific/Engineering :: Medical Science Apps.
Classifier: Topic :: Software Development :: Libraries :: Python Modules
Requires-Python: >=3.8
Requires-Dist: numpy>=1.20.0
